{
"meta":{"test_sets":[],"test_metrics":[],"learn_metrics":[{"best_value":"Min","name":"RMSE"}],"launch_mode":"Train","parameters":"","iteration_count":100,"learn_sets":["learn"],"name":"experiment"},
"iterations":[
{"learn":[12.36888394],"iteration":0,"passed_time":0.0009226398362,"remaining_time":0.09134134378},
{"learn":[10.33627131],"iteration":1,"passed_time":0.001664156133,"remaining_time":0.08154365051},
{"learn":[8.652855341],"iteration":2,"passed_time":0.002466640793,"remaining_time":0.07975471896},
{"learn":[7.515253035],"iteration":3,"passed_time":0.00317916654,"remaining_time":0.07629999697},
{"learn":[6.641269179],"iteration":4,"passed_time":0.003893916223,"remaining_time":0.07398440823},
{"learn":[5.976997781],"iteration":5,"passed_time":0.004643809139,"remaining_time":0.07275300984},
{"learn":[5.473731298],"iteration":6,"passed_time":0.005347295023,"remaining_time":0.07104263388},
{"learn":[5.064891106],"iteration":7,"passed_time":0.006054909166,"remaining_time":0.06963145541},
{"learn":[4.770678128],"iteration":8,"passed_time":0.006775269728,"remaining_time":0.06850550503},
{"learn":[4.531743953],"iteration":9,"passed_time":0.007502183324,"remaining_time":0.06751964991},
{"learn":[4.394398409],"iteration":10,"passed_time":0.008208290155,"remaining_time":0.06641252944},
{"learn":[4.261521317],"iteration":11,"passed_time":0.008910200002,"remaining_time":0.06534146668},
{"learn":[4.15499236],"iteration":12,"passed_time":0.009629858621,"remaining_time":0.06444597692},
{"learn":[4.070162196],"iteration":13,"passed_time":0.01031987145,"remaining_time":0.06339349607},
{"learn":[3.970448302],"iteration":14,"passed_time":0.01100789322,"remaining_time":0.06237806159},
{"learn":[3.84374153],"iteration":15,"passed_time":0.01169526175,"remaining_time":0.06140012421},
{"learn":[3.78342196],"iteration":16,"passed_time":0.01242089957,"remaining_time":0.06064321557},
{"learn":[3.745824249],"iteration":17,"passed_time":0.01313963005,"remaining_time":0.05985831468},
{"learn":[3.736150778],"iteration":18,"passed_time":0.01351021371,"remaining_time":0.05759617426},
{"learn":[3.66014466],"iteration":19,"passed_time":0.01425246732,"remaining_time":0.05700986928},
{"learn":[3.641247906],"iteration":20,"passed_time":0.01497129121,"remaining_time":0.0563205717},
{"learn":[3.596342631],"iteration":21,"passed_time":0.01567474974,"remaining_time":0.05557411271},
{"learn":[3.552080408],"iteration":22,"passed_time":0.01638366568,"remaining_time":0.05484966337},
{"learn":[3.489158823],"iteration":23,"passed_time":0.01687918334,"remaining_time":0.05345074726},
{"learn":[3.464589179],"iteration":24,"passed_time":0.01757426392,"remaining_time":0.05272279175},
{"learn":[3.381445014],"iteration":25,"passed_time":0.01829367432,"remaining_time":0.05206661153},
{"learn":[3.342572109],"iteration":26,"passed_time":0.01899890239,"remaining_time":0.05136740275},
{"learn":[3.324537063],"iteration":27,"passed_time":0.0196937581,"remaining_time":0.05064109226},
{"learn":[3.284460468],"iteration":28,"passed_time":0.02039086911,"remaining_time":0.04992247264},
{"learn":[3.215582881],"iteration":29,"passed_time":0.02108336343,"remaining_time":0.04919451467},
{"learn":[3.166552262],"iteration":30,"passed_time":0.02182184576,"remaining_time":0.04857120507},
{"learn":[3.140025301],"iteration":31,"passed_time":0.02251685227,"remaining_time":0.04784831106},
{"learn":[3.090431409],"iteration":32,"passed_time":0.02321147778,"remaining_time":0.04712633367},
{"learn":[3.047270201],"iteration":33,"passed_time":0.02394074208,"remaining_time":0.04647320522},
{"learn":[3.014743154],"iteration":34,"passed_time":0.02465134883,"remaining_time":0.0457810764},
{"learn":[2.957222401],"iteration":35,"passed_time":0.02532946398,"remaining_time":0.04503015819},
{"learn":[2.922190609],"iteration":36,"passed_time":0.02604462068,"remaining_time":0.04434624603},
{"learn":[2.901229267],"iteration":37,"passed_time":0.02675965595,"remaining_time":0.04366049128},
{"learn":[2.875873909],"iteration":38,"passed_time":0.02745487664,"remaining_time":0.04294224295},
{"learn":[2.823620936],"iteration":39,"passed_time":0.02814689188,"remaining_time":0.04222033783},
{"learn":[2.77808977],"iteration":40,"passed_time":0.02889849095,"remaining_time":0.04158563332},
{"learn":[2.748126221],"iteration":41,"passed_time":0.02960235783,"remaining_time":0.04087944653},
{"learn":[2.722463159],"iteration":42,"passed_time":0.0302710995,"remaining_time":0.04012680631},
{"learn":[2.703145499],"iteration":43,"passed_time":0.03097609069,"remaining_time":0.03942411543},
{"learn":[2.696100898],"iteration":44,"passed_time":0.0316817478,"remaining_time":0.0387221362},
{"learn":[2.668505125],"iteration":45,"passed_time":0.03238924517,"remaining_time":0.03802215738},
{"learn":[2.637568673],"iteration":46,"passed_time":0.03313670464,"remaining_time":0.03736692225},
{"learn":[2.567072441],"iteration":47,"passed_time":0.0338183155,"remaining_time":0.03663650846},
{"learn":[2.558411738],"iteration":48,"passed_time":0.03450754565,"remaining_time":0.0359160169},
{"learn":[2.532781464],"iteration":49,"passed_time":0.03523167749,"remaining_time":0.03523167749},
{"learn":[2.528952353],"iteration":50,"passed_time":0.03591873842,"remaining_time":0.03451016045},
{"learn":[2.484400885],"iteration":51,"passed_time":0.03661028392,"remaining_time":0.03379410824},
{"learn":[2.438961927],"iteration":52,"passed_time":0.03732563213,"remaining_time":0.03310008887},
{"learn":[2.422313843],"iteration":53,"passed_time":0.03803680536,"remaining_time":0.03240172309},
{"learn":[2.380154097],"iteration":54,"passed_time":0.03873735603,"remaining_time":0.03169420039},
{"learn":[2.364544886],"iteration":55,"passed_time":0.03944490478,"remaining_time":0.03099242519},
{"learn":[2.327346441],"iteration":56,"passed_time":0.04015222,"remaining_time":0.03029027123},
{"learn":[2.310167482],"iteration":57,"passed_time":0.04082025438,"remaining_time":0.02955949455},
{"learn":[2.305765097],"iteration":58,"passed_time":0.04153648735,"remaining_time":0.02886433867},
{"learn":[2.279468135],"iteration":59,"passed_time":0.04223254211,"remaining_time":0.02815502807},
{"learn":[2.246394511],"iteration":60,"passed_time":0.04291958102,"remaining_time":0.02744038787},
{"learn":[2.199484032],"iteration":61,"passed_time":0.04361642513,"remaining_time":0.02673264766},
{"learn":[2.183477453],"iteration":62,"passed_time":0.04429972212,"remaining_time":0.02601729712},
{"learn":[2.158672622],"iteration":63,"passed_time":0.04501788077,"remaining_time":0.02532255793},
{"learn":[2.153904817],"iteration":64,"passed_time":0.04573354458,"remaining_time":0.02462575477},
{"learn":[2.130760435],"iteration":65,"passed_time":0.04651231795,"remaining_time":0.02396089106},
{"learn":[2.103197762],"iteration":66,"passed_time":0.04735066847,"remaining_time":0.02332197104},
{"learn":[2.090589299],"iteration":67,"passed_time":0.0481956541,"remaining_time":0.02268030781},
{"learn":[2.060640222],"iteration":68,"passed_time":0.04952555683,"remaining_time":0.02225061249},
{"learn":[2.03358277],"iteration":69,"passed_time":0.05047439212,"remaining_time":0.02163188234},
{"learn":[1.997927935],"iteration":70,"passed_time":0.05124502841,"remaining_time":0.02093106794},
{"learn":[1.981494002],"iteration":71,"passed_time":0.05200157712,"remaining_time":0.02022283555},
{"learn":[1.966145781],"iteration":72,"passed_time":0.05269761853,"remaining_time":0.0194909},
{"learn":[1.944550357],"iteration":73,"passed_time":0.05339734381,"remaining_time":0.0187612289},
{"learn":[1.929901565],"iteration":74,"passed_time":0.05410263526,"remaining_time":0.01803421175},
{"learn":[1.91284364],"iteration":75,"passed_time":0.05484608657,"remaining_time":0.01731981681},
{"learn":[1.888337373],"iteration":76,"passed_time":0.05558348662,"remaining_time":0.01660285964},
{"learn":[1.873779132],"iteration":77,"passed_time":0.05629675969,"remaining_time":0.01587857325},
{"learn":[1.848846399],"iteration":78,"passed_time":0.05697878824,"remaining_time":0.01514626017},
{"learn":[1.837356183],"iteration":79,"passed_time":0.05770341919,"remaining_time":0.0144258548},
{"learn":[1.806539541],"iteration":80,"passed_time":0.05845296447,"remaining_time":0.0137111892},
{"learn":[1.794331243],"iteration":81,"passed_time":0.05910902644,"remaining_time":0.01297515214},
{"learn":[1.76750643],"iteration":82,"passed_time":0.05983145747,"remaining_time":0.01225463587},
{"learn":[1.75808035],"iteration":83,"passed_time":0.06054337268,"remaining_time":0.01153207099},
{"learn":[1.74203696],"iteration":84,"passed_time":0.06148155837,"remaining_time":0.01084968677},
{"learn":[1.717751877],"iteration":85,"passed_time":0.06230386761,"remaining_time":0.01014249008},
{"learn":[1.701273905],"iteration":86,"passed_time":0.06299668488,"remaining_time":0.009413297741},
{"learn":[1.686308155],"iteration":87,"passed_time":0.06373977388,"remaining_time":0.008691787347},
{"learn":[1.677631146],"iteration":88,"passed_time":0.06447984826,"remaining_time":0.007969419448},
{"learn":[1.664075816],"iteration":89,"passed_time":0.06518450383,"remaining_time":0.007242722647},
{"learn":[1.65453173],"iteration":90,"passed_time":0.06596088845,"remaining_time":0.006523604352},
{"learn":[1.631706581],"iteration":91,"passed_time":0.06667901173,"remaining_time":0.005798174933},
{"learn":[1.625990351],"iteration":92,"passed_time":0.06740173101,"remaining_time":0.005073248571},
{"learn":[1.624194736],"iteration":93,"passed_time":0.06808817341,"remaining_time":0.004346053622},
{"learn":[1.620483306],"iteration":94,"passed_time":0.06878783263,"remaining_time":0.003620412244},
{"learn":[1.604675119],"iteration":95,"passed_time":0.069498775,"remaining_time":0.002895782292},
{"learn":[1.584132728],"iteration":96,"passed_time":0.07024538239,"remaining_time":0.0021725376},
{"learn":[1.580165887],"iteration":97,"passed_time":0.07091758707,"remaining_time":0.001447297695},
{"learn":[1.559294295],"iteration":98,"passed_time":0.0716536246,"remaining_time":0.0007237739859},
{"learn":[1.546495141],"iteration":99,"passed_time":0.07236541705,"remaining_time":0}
]}